insuree/__init__.py
insuree/admin.py
insuree/apps.py
insuree/dataloaders.py
insuree/gql_mutations.py
insuree/gql_queries.py
insuree/models.py
insuree/report.py
insuree/schema.py
insuree/services.py
insuree/signals.py
insuree/test_helpers.py
insuree/urls.py
insuree/utils.py
insuree/views.py
insuree/management/__init__.py
insuree/management/commands/__init__.py
insuree/management/commands/generateinsurees.py
insuree/migrations/0001_initial.py
insuree/migrations/0002_family_familytype_photo.py
insuree/migrations/0003_insureepolicy.py
insuree/migrations/0004_confirmationtype_education_profession_relation.py
insuree/migrations/0005_identificationtype.py
insuree/migrations/0006_auto_20200722_0839.py
insuree/migrations/0007_auto_20200722_0940.py
insuree/migrations/0008_auto_20200731_0443.py
insuree/migrations/0009_familymutation_insureemutation.py
insuree/migrations/0010_auto_20200731_0524.py
insuree/migrations/0011_auto_20200807_1309.py
insuree/migrations/0012_policyrenewaldetail.py
insuree/migrations/0013_auto_20211103_1023.py
insuree/migrations/0014_add_missing_fields_to_django_scheme.py
insuree/migrations/0015_set_managed_to_true_in_all_models.py
insuree/migrations/0016_alter_jsonext_column.py
insuree/migrations/0017_auto_20230923_2238.py
insuree/migrations/0018_confirmationtype_is_confirmation_number_required.py
insuree/migrations/0019_auto_20231026_1205.py
insuree/migrations/0020_alter_insuree_card_issued.py
insuree/migrations/0021_alter_insureephoto_chf_id.py
insuree/migrations/0022_alter_insureephoto_date_and_more.py
insuree/migrations/0023_alter_family_head_insuree.py
insuree/migrations/__init__.py
insuree/reports/__init__.py
insuree/reports/enrolled_families.py
insuree/reports/insuree_family_overview.py
insuree/reports/insuree_missing_photo.py
insuree/reports/insurees_pending_enrollment.py
insuree/tests/__init__.py
insuree/tests/test_graphql.py
insuree/tests/test_insuree_photo.py
insuree/tests/test_insuree_validation.py
insuree/tests/test_reports.py
openimis_be_insuree-1.10.0.dist-info/licenses/LICENSE.md
openimis_be_insuree-1.10.0.dist-info/METADATA
openimis_be_insuree-1.10.0.dist-info/WHEEL
openimis_be_insuree-1.10.0.dist-info/top_level.txt
openimis_be_insuree-1.10.0.dist-info/RECORD
